./.gitignore
./LICENSE
./PKG-INFO
./README.md
./ask.py
./i18n.py
./pyproject.toml
ask_py_cli-0.2.1.dist-info/METADATA
ask_py_cli-0.2.1.dist-info/WHEEL
ask_py_cli-0.2.1.dist-info/entry_points.txt
ask_py_cli-0.2.1.dist-info/licenses/LICENSE
ask_py_cli-0.2.1.dist-info/RECORD
