Metadata-Version: 2.4
Name: ask-py-cli
Version: 0.2.1
Summary: 基于 LangChain 的终端 LLM 问答工具，支持多模型、角色记忆和 MCP 工具
Project-URL: Homepage, https://github.com/tiancheng91/ask.py
Project-URL: Repository, https://github.com/tiancheng91/ask.py
Project-URL: Issues, https://github.com/tiancheng91/ask.py/issues
Author-email: tiancheng91 <tiancheng91@users.noreply.github.com>
License: MIT
License-File: LICENSE
Keywords: chatbot,cli,gpt,langchain,llm,mcp,openai
Classifier: Development Status :: 4 - Beta
Classifier: Environment :: Console
Classifier: Intended Audience :: Developers
Classifier: License :: OSI Approved :: MIT License
Classifier: Operating System :: OS Independent
Classifier: Programming Language :: Python :: 3
Classifier: Programming Language :: Python :: 3.10
Classifier: Programming Language :: Python :: 3.11
Classifier: Programming Language :: Python :: 3.12
Classifier: Topic :: Scientific/Engineering :: Artificial Intelligence
Requires-Python: >=3.10
Requires-Dist: click>=8.0.0
Requires-Dist: langchain-openai>=0.2.0
Requires-Dist: langchain>=0.3.0
Requires-Dist: langgraph>=0.2.0
Requires-Dist: mcp>=1.0.0
Requires-Dist: pyyaml>=6.0
Requires-Dist: rich>=13.0.0
Provides-Extra: dev
Requires-Dist: pytest-asyncio>=0.21.0; extra == 'dev'
Requires-Dist: pytest>=7.0.0; extra == 'dev'
